<?xml version="1.0" encoding="utf-8"?>
<Entity parent="template_structure_civic_civil_centre">
  <Builder>
    <Rate>1.0</Rate>
    <Entities datatype="tokens">
      structures/{civ}/house
      structures/{civ}/apartment
      structures/{civ}/storehouse
      structures/{civ}/farmstead
      structures/{civ}/corral
      structures/{civ}/dock
      structures/{civ}/barracks
      structures/{civ}/arsenal
      structures/{civ}/forge
      structures/{civ}/temple
      structures/{civ}/market
      structures/{civ}/outpost
      structures/{civ}/sentry_tower
      structures/{civ}/defense_tower
      structures/{civ}/fortress
      structures/{civ}/wonder
    </Entities>
  </Builder>
  <Cost>
    <BuildTime>600</BuildTime>
    <Resources>
      <stone>900</stone>
      <metal>300</metal>
    </Resources>
  </Cost>
  <Population>
    <Bonus>50</Bonus>
  </Population>
  <Identity>
    <Classes datatype="tokens">HopiCivCentre</Classes>
    <Civ>hopi</Civ>
    <GenericName>House Block</GenericName>
    <SpecificName>Pueblo</SpecificName>
  </Identity>
  <Trainer>
    <Entities datatype="tokens">
      units/{civ}/infantry_spearman_b
      units/{civ}/infantry_archer_b
      units/{civ}/infantry_slinger_b
    </Entities>
  </Trainer>
  <VisualActor>
    <Actor>structures/hopis/civic_center.xml</Actor>
  </VisualActor>
</Entity>
