<?xml version="1.0" encoding="utf-8"?>
<Entity parent="template_structure_defense_wallset">
  <Identity>
    <Civ>mex</Civ>
    <SpecificName>?</SpecificName>
  </Identity>
  <WallSet>
    <Templates>
      <Tower>structures/azte_wall_tower</Tower>
      <Gate>structures/azte_wall_gate</Gate>
      <WallLong>structures/azte_wall_long</WallLong>
      <WallMedium>structures/azte_wall_medium</WallMedium>
      <WallShort>structures/azte_wall_short</WallShort>
    </Templates>
    <MaxTowerOverlap>0.90</MaxTowerOverlap>
    <MinTowerOverlap>0.05</MinTowerOverlap>
  </WallSet>
</Entity>
