{
	"genericName": "Water Stack",
	"description": "Increases water trickle rates for structures.",
	"cost": {
		"wood": 600,
		"metal": 300
	},
	"supersedes": "gather_hydric_waterhole",
	"requirements": { "tech": "phase_city" },
	"requirementsTooltip": "Unlocked in City Phase.",
	"icon": "water_well.png",
	"researchTime": 60,
	"tooltip": "Storehouse +25% water trickle rate.",
	"modifications": [
		{ "value": "ResourceTrickle/Rates/water.clean", "multiply": 1.25 }
	],
	"affects": ["Storehouse"],
	"soundComplete": "interface/alarm/alarm_upgradearmory.xml"
}
